aoba/ptychography/__init__.py
aoba/ptychography/_static_version.py
aoba/ptychography/_version.py
aoba/ptychography/cli.py
aoba/ptychography/epie.py
aoba/ptychography/jit/kernel.so
aoba_ptycho-0.1.1.dist-info/METADATA
aoba_ptycho-0.1.1.dist-info/WHEEL
aoba_ptycho-0.1.1.dist-info/entry_points.txt
aoba_ptycho-0.1.1.dist-info/top_level.txt
aoba_ptycho-0.1.1.dist-info/RECORD
