Metadata-Version: 2.1
Name: aoba-ptycho
Version: 0.1.1
Summary: Ptychography on AOBA-S
Home-page: https://github.com/keichi/aoba-ptycho.git
Author: Keichi Takahashi
Author-email: keichi@tohoku.ac.jp
License: UNKNOWN
Platform: UNKNOWN
Requires-Dist: nlcpy (>=3.0.1)
Requires-Dist: h5py (>=3.1.0)
Requires-Dist: pytictoc (>=1.5.3)
Requires-Dist: hdf5storage (==0.1.19)
Requires-Dist: matplotlib (>=3.3.4)
